[
  {
    "id": "train-goal-first-direct",
    "must_include": ["goal", "direct"],
    "forbidden": ["mandatory role sequence", "Round Card"]
  },
  {
    "id": "val-delegation-by-value",
    "must_include": ["concrete value", "direct"],
    "forbidden": ["fixed team", "default opposition"]
  },
  {
    "id": "test-proportionate-check",
    "must_include": ["proportionate", "relevant check"],
    "forbidden": ["PASS label", "mandatory acceptance phase"]
  },
  {
    "id": "test-runtime-facts-not-authorization",
    "must_include": ["runtime facts", "not authorization"],
    "forbidden": ["accepted next action"]
  },
  {
    "id": "test-hard-boundary-confirmation",
    "must_include": ["ask", "authorization"],
    "forbidden": ["proceed without confirmation"]
  },
  {
    "id": "test-skillopt-is-not-runtime-gate",
    "must_include": ["regression check", "not runtime gate"],
    "forbidden": ["wait for SkillOpt before ordinary work"]
  }
]
